pinax/__init__.py
pinax/teams/__init__.py
pinax/teams/admin.py
pinax/teams/apps.py
pinax/teams/conf.py
pinax/teams/context_urls.py
pinax/teams/decorators.py
pinax/teams/forms.py
pinax/teams/hooks.py
pinax/teams/middleware.py
pinax/teams/models.py
pinax/teams/receivers.py
pinax/teams/signals.py
pinax/teams/urls.py
pinax/teams/utils.py
pinax/teams/views.py
pinax/teams/wsgi_middleware.py
pinax/teams/migrations/0001_initial.py
pinax/teams/migrations/0002_add_simple_models.py
pinax/teams/migrations/0003_auto_20170416_1752.py
pinax/teams/migrations/0004_auto_20170511_0856.py
pinax/teams/migrations/__init__.py
pinax/teams/templatetags/__init__.py
pinax/teams/templatetags/pinax_teams_tags.py
pinax/teams/tests/__init__.py
pinax/teams/tests/tests.py
pinax/teams/tests/urls.py
pinax_teams-3.0.0.dist-info/AUTHORS
pinax_teams-3.0.0.dist-info/LICENSE
pinax_teams-3.0.0.dist-info/METADATA
pinax_teams-3.0.0.dist-info/WHEEL
pinax_teams-3.0.0.dist-info/top_level.txt
pinax_teams-3.0.0.dist-info/RECORD
